osis_book_tools/__init__.py
osis_book_tools/db.sqlite
osis_book_tools-1.0.1.dist-info/METADATA
osis_book_tools-1.0.1.dist-info/WHEEL
osis_book_tools-1.0.1.dist-info/top_level.txt
osis_book_tools-1.0.1.dist-info/RECORD
