Metadata-Version: 2.1
Name: osis-book-tools
Version: 1.0.1
Summary: A set of tools for converting between OSIS abbreviations and localized biblical book names
Home-page: http://api.sermonaudio.com/
Author: SermonAudio.com
Author-email: info@sermonaudio.com
License: MIT
Keywords: bible OSIS SBL
Platform: UNKNOWN
Classifier: Development Status :: 5 - Production/Stable
Classifier: Intended Audience :: Developers
Classifier: License :: OSI Approved :: MIT License
Classifier: Programming Language :: Python :: 3.6
